MANIFEST.in
README.rst
setup.py
aliyun_python_sdk_dds_test.egg-info/PKG-INFO
aliyun_python_sdk_dds_test.egg-info/SOURCES.txt
aliyun_python_sdk_dds_test.egg-info/dependency_links.txt
aliyun_python_sdk_dds_test.egg-info/requires.txt
aliyun_python_sdk_dds_test.egg-info/top_level.txt
aliyunsdkdds/__init__.py
aliyunsdkdds/request/__init__.py
aliyunsdkdds/request/v20151201/AllocatePublicNetworkAddressRequest.py
aliyunsdkdds/request/v20151201/CheckRecoveryConditionRequest.py
aliyunsdkdds/request/v20151201/CreateAccountRequest.py
aliyunsdkdds/request/v20151201/CreateBackupRequest.py
aliyunsdkdds/request/v20151201/CreateDBInstanceRequest.py
aliyunsdkdds/request/v20151201/CreateNodeRequest.py
aliyunsdkdds/request/v20151201/CreateRecommendationTaskRequest.py
aliyunsdkdds/request/v20151201/CreateShardingDBInstanceRequest.py
aliyunsdkdds/request/v20151201/CreateStaticVerificationRequest.py
aliyunsdkdds/request/v20151201/DeleteDBInstanceRequest.py
aliyunsdkdds/request/v20151201/DeleteNodeRequest.py
aliyunsdkdds/request/v20151201/DescribeAccountsRequest.py
aliyunsdkdds/request/v20151201/DescribeActiveOperationTaskCountRequest.py
aliyunsdkdds/request/v20151201/DescribeActiveOperationTaskRegionRequest.py
aliyunsdkdds/request/v20151201/DescribeActiveOperationTaskRequest.py
aliyunsdkdds/request/v20151201/DescribeActiveOperationTaskTypeRequest.py
aliyunsdkdds/request/v20151201/DescribeAuditFilesRequest.py
aliyunsdkdds/request/v20151201/DescribeAuditLogFilterRequest.py
aliyunsdkdds/request/v20151201/DescribeAuditPolicyRequest.py
aliyunsdkdds/request/v20151201/DescribeAuditRecordsRequest.py
aliyunsdkdds/request/v20151201/DescribeAvailableEngineVersionRequest.py
aliyunsdkdds/request/v20151201/DescribeAvailableTimeRangeRequest.py
aliyunsdkdds/request/v20151201/DescribeAvaliableTimeRangeRequest.py
aliyunsdkdds/request/v20151201/DescribeBackupDBsRequest.py
aliyunsdkdds/request/v20151201/DescribeBackupPolicyRequest.py
aliyunsdkdds/request/v20151201/DescribeBackupsRequest.py
aliyunsdkdds/request/v20151201/DescribeDBInstanceAttributeRequest.py
aliyunsdkdds/request/v20151201/DescribeDBInstanceMonitorRequest.py
aliyunsdkdds/request/v20151201/DescribeDBInstancePerformanceRequest.py
